LICENSE
MANIFEST.in
README.md
db_create.py
db_migrate.py
requirements.txt
setup.cfg
setup.py
test-requirements.txt
jino/__init__.py
jino/config.py
jino/forms.py
jino/jenkins_lib.py
jino/main.py
jino/models.py
jino/parser.py
jino/utils.py
jino.egg-info/PKG-INFO
jino.egg-info/SOURCES.txt
jino.egg-info/dependency_links.txt
jino.egg-info/entry_points.txt
jino.egg-info/not-zip-safe
jino.egg-info/pbr.json
jino.egg-info/requires.txt
jino.egg-info/top_level.txt
jino/static/css/bootstrap-table.css
jino/static/css/bootstrap.css
jino/static/css/bootstrap.css.map
jino/static/css/bootstrap.min.css
jino/static/css/bootstrap.min.css.map
jino/static/css/jino.css
jino/static/css/patternfly-additions.min.css
jino/static/css/patternfly.min.css
jino/static/fonts/OpenSans-Bold-webfont.ttf
jino/static/fonts/OpenSans-Bold-webfont.woff
jino/static/fonts/OpenSans-Light-webfont.ttf
jino/static/fonts/OpenSans-Light-webfont.woff
jino/static/fonts/OpenSans-Regular-webfont.ttf
jino/static/fonts/OpenSans-Regular-webfont.woff
jino/static/fonts/OpenSans-Semibold-webfont.ttf
jino/static/fonts/OpenSans-Semibold-webfont.woff
jino/static/fonts/PatternFlyIcons-webfont.ttf
jino/static/fonts/PatternFlyIcons-webfont.woff
jino/static/fonts/fontawesome-webfont.ttf
jino/static/fonts/fontawesome-webfont.woff
jino/static/fonts/fontawesome-webfont.woff2
jino/static/js/angular.min.js
jino/static/js/bootstrap-table.js
jino/static/js/bootstrap.js
jino/static/js/bootstrap.min.js
jino/static/js/jquery.matchHeight-min.js
jino/static/js/jquery.min.js
jino/static/js/patternfly.min.js
jino/static/logo/jino.png
jino/templates/home.html
jino/templates/layout.html
jino/templates/navbar.html
jino/templates/provision.html
jino/views/__init__.py
jino/views/home.py
jino/views/provision.py
samples/config.cfg
samples/jobs.yaml