Metadata-Version: 1.1
Name: jino
Version: 0.0.1.dev12
Summary: TBA
Home-page: UNKNOWN
Author: Arie Bregman
Author-email: bregman.arie@gmail.com
License: Apache License, Version 2.0
Platform: UNKNOWN
Classifier: Topic :: Scientific/Engineering
Classifier: Topic :: System :: Distributed Computing
Classifier: Topic :: System :: Monitoring
Classifier: Environment :: Web Environment
Classifier: Intended Audience :: Developers
Classifier: Intended Audience :: Information Technology
Classifier: Intended Audience :: Science/Research
Classifier: Intended Audience :: System Administrators
Classifier: License :: OSI Approved :: Apache Software License
Classifier: Operating System :: OS Independent
Classifier: Programming Language :: Python
Classifier: Programming Language :: Python :: 2
Classifier: Programming Language :: Python :: 2.7
